[
	{
		"venue_id": "yelpk_QKyQNyvHEHLxVG_UVNnQ",
		"event_name": "HunkOMania Male Strip Club",
		"event_id": "yelpk_QKyQNyvHEHLxVG_UVNnQ",
		"mon_start": 540,
		"mon_end": 1410,
		"tues_start": 540,
		"tues_end": 1410,
		"wed_start": 540,
		"wed_end": 1410,
		"thurs_start": 540,
		"thurs_end": 1410,
		"fri_start": 540,
		"fri_end": 1410,
		"sat_start": 540,
		"sat_end": 1410,
		"sun_start": 540,
		"sun_end": 1410,
		"tags": [
			"stripclubs",
			"nightlife"
		],
		"price": -3
	},
	{
		"venue_id": "yelpxQpkwGn2MYhfp7NT_6vUSQ",
		"event_name": "Hunkamania",
		"event_id": "yelpxQpkwGn2MYhfp7NT_6vUSQ",
		"mon_start": 0,
		"mon_end": 0,
		"tues_start": 0,
		"tues_end": 0,
		"wed_start": 0,
		"wed_end": 0,
		"thurs_start": 0,
		"thurs_end": 0,
		"fri_start": 0,
		"fri_end": 0,
		"sat_start": 0,
		"sat_end": 0,
		"sun_start": 0,
		"sun_end": 0,
		"tags": [
			"adultentertainment",
			"nightlife"
		],
		"price": -10
	},
	{
		"venue_id": "yelpzVVuprMzLkVl_VQfps73YQ",
		"event_name": "The Ram Book Store",
		"event_id": "yelpzVVuprMzLkVl_VQfps73YQ",
		"mon_start": 0,
		"mon_end": 0,
		"tues_start": 0,
		"tues_end": 0,
		"wed_start": 0,
		"wed_end": 0,
		"thurs_start": 0,
		"thurs_end": 0,
		"fri_start": 0,
		"fri_end": 0,
		"sat_start": 0,
		"sat_end": 0,
		"sun_start": 0,
		"sun_end": 0,
		"tags": [
			"adultentertainment",
			"nightlife"
		],
		"price": -10
	},
	{
		"venue_id": "yelpKesDl02UKzzyG_0UpgsrcQ",
		"event_name": "Bare-Assets",
		"event_id": "yelpKesDl02UKzzyG_0UpgsrcQ",
		"mon_start": 0,
		"mon_end": 0,
		"tues_start": 0,
		"tues_end": 0,
		"wed_start": 0,
		"wed_end": 0,
		"thurs_start": 0,
		"thurs_end": 0,
		"fri_start": 0,
		"fri_end": 0,
		"sat_start": 0,
		"sat_end": 0,
		"sun_start": 0,
		"sun_end": 0,
		"tags": [
			"adultentertainment",
			"nightlife"
		],
		"price": -2
	},
	{
		"venue_id": "yelpltv6iSeaFWZlXETObGqFVw",
		"event_name": "Hunks and Babes Ent.",
		"event_id": "yelpltv6iSeaFWZlXETObGqFVw",
		"mon_start": 0,
		"mon_end": 0,
		"tues_start": 0,
		"tues_end": 0,
		"wed_start": 0,
		"wed_end": 0,
		"thurs_start": 0,
		"thurs_end": 0,
		"fri_start": 0,
		"fri_end": 0,
		"sat_start": 0,
		"sat_end": 0,
		"sun_start": 0,
		"sun_end": 0,
		"tags": [
			"adultentertainment",
			"nightlife"
		],
		"price": -10
	},
	{
		"venue_id": "yelpgeqjDwRTkZWrFokaa8COBA",
		"event_name": "Dreamboys Chicago",
		"event_id": "yelpgeqjDwRTkZWrFokaa8COBA",
		"mon_start": 1200,
		"mon_end": 1320,
		"tues_start": 0,
		"tues_end": 0,
		"wed_start": 0,
		"wed_end": 0,
		"thurs_start": 0,
		"thurs_end": 0,
		"fri_start": 0,
		"fri_end": 0,
		"sat_start": 0,
		"sat_end": 0,
		"sun_start": 0,
		"sun_end": 0,
		"tags": [
			"stripclubs",
			"nightlife"
		],
		"price": -10
	},
	{
		"venue_id": "yelpuSa2Y-5DSLj8bmmNXvS7qw",
		"event_name": "Better Boobie Bureau",
		"event_id": "yelpuSa2Y-5DSLj8bmmNXvS7qw",
		"mon_start": 1230,
		"mon_end": 1350,
		"tues_start": 1230,
		"tues_end": 1350,
		"wed_start": 0,
		"wed_end": 0,
		"thurs_start": 0,
		"thurs_end": 0,
		"fri_start": 0,
		"fri_end": 0,
		"sat_start": 0,
		"sat_end": 0,
		"sun_start": 0,
		"sun_end": 0,
		"tags": [
			"theater",
			"nightlife",
			"adultentertainment",
			"nightlife"
		],
		"price": -10
	},
	{
		"venue_id": "yelpHgLwrBtCc_0Ujgney4kcFQ",
		"event_name": "Next Plateau Chicago",
		"event_id": "yelpHgLwrBtCc_0Ujgney4kcFQ",
		"mon_start": 0,
		"mon_end": 0,
		"tues_start": 0,
		"tues_end": 0,
		"wed_start": 0,
		"wed_end": 0,
		"thurs_start": 0,
		"thurs_end": 0,
		"fri_start": 0,
		"fri_end": 0,
		"sat_start": 0,
		"sat_end": 0,
		"sun_start": 0,
		"sun_end": 0,
		"tags": [
			"adultentertainment",
			"nightlife"
		],
		"price": -4
	},
	{
		"venue_id": "yelpJXATvup_5Or3ss05E9dEXw",
		"event_name": "B. D. Massage and Spa",
		"event_id": "yelpJXATvup_5Or3ss05E9dEXw",
		"mon_start": 0,
		"mon_end": 0,
		"tues_start": 0,
		"tues_end": 0,
		"wed_start": 0,
		"wed_end": 0,
		"thurs_start": 0,
		"thurs_end": 0,
		"fri_start": 0,
		"fri_end": 0,
		"sat_start": 0,
		"sat_end": 0,
		"sun_start": 0,
		"sun_end": 0,
		"tags": [
			"adultentertainment",
			"nightlife",
			"massage",
			"nightlife"
		],
		"price": -3
	},
	{
		"venue_id": "yelpbtKafi69L4OqY3MbyHrZQg",
		"event_name": "Under the Rose Entertainment",
		"event_id": "yelpbtKafi69L4OqY3MbyHrZQg",
		"mon_start": 0,
		"mon_end": 0,
		"tues_start": 0,
		"tues_end": 0,
		"wed_start": 0,
		"wed_end": 0,
		"thurs_start": 0,
		"thurs_end": 0,
		"fri_start": 0,
		"fri_end": 0,
		"sat_start": 0,
		"sat_end": 0,
		"sun_start": 0,
		"sun_end": 0,
		"tags": [
			"adultentertainment",
			"nightlife"
		],
		"price": -10
	},
	{
		"venue_id": "yelp3QsJZOr4b9BK-qTPCDU03w",
		"event_name": "Fire Strippers",
		"event_id": "yelp3QsJZOr4b9BK-qTPCDU03w",
		"mon_start": 0,
		"mon_end": 0,
		"tues_start": 0,
		"tues_end": 0,
		"wed_start": 0,
		"wed_end": 0,
		"thurs_start": 0,
		"thurs_end": 0,
		"fri_start": 0,
		"fri_end": 0,
		"sat_start": 0,
		"sat_end": 0,
		"sun_start": 0,
		"sun_end": 0,
		"tags": [
			"stripteasedancers",
			"nightlife"
		],
		"price": -3
	},
	{
		"venue_id": "yelpXMJFYOeyFMAoke2naZSjLg",
		"event_name": "Doll House",
		"event_id": "yelpXMJFYOeyFMAoke2naZSjLg",
		"mon_start": 0,
		"mon_end": 0,
		"tues_start": 0,
		"tues_end": 0,
		"wed_start": 0,
		"wed_end": 0,
		"thurs_start": 0,
		"thurs_end": 0,
		"fri_start": 0,
		"fri_end": 0,
		"sat_start": 0,
		"sat_end": 0,
		"sun_start": 0,
		"sun_end": 0,
		"tags": [
			"adultentertainment",
			"nightlife"
		],
		"price": -10
	}
]