[
	{
		"venue_id": "yelpf69LjfUFOumQB69QgMWIUw",
		"event_name": "Paintball Explosion Park",
		"event_id": "yelpf69LjfUFOumQB69QgMWIUw",
		"mon_start": 540,
		"mon_end": 1020,
		"tues_start": 540,
		"tues_end": 1020,
		"wed_start": 540,
		"wed_end": 1020,
		"thurs_start": 660,
		"thurs_end": 1140,
		"fri_start": 660,
		"fri_end": 1140,
		"sat_start": 540,
		"sat_end": 1260,
		"sun_start": 540,
		"sun_end": 1020,
		"tags": [
			"paintball",
			"misc",
			"hobbyshops",
			"misc"
		],
		"price": -2
	},
	{
		"venue_id": "yelpEk94Z4QqmlhDXGgANqm38g",
		"event_name": "Ohare Paintball Park",
		"event_id": "yelpEk94Z4QqmlhDXGgANqm38g",
		"mon_start": 1020,
		"mon_end": 1320,
		"tues_start": 1020,
		"tues_end": 1320,
		"wed_start": 720,
		"wed_end": 1320,
		"thurs_start": 720,
		"thurs_end": 1140,
		"fri_start": 0,
		"fri_end": 0,
		"sat_start": 0,
		"sat_end": 0,
		"sun_start": 0,
		"sun_end": 0,
		"tags": [
			"paintball",
			"misc"
		],
		"price": -10
	},
	{
		"venue_id": "yelpEJK-1a0eB-yLDjSuNzbaow",
		"event_name": "Badlandz Paintball Field",
		"event_id": "yelpEJK-1a0eB-yLDjSuNzbaow",
		"mon_start": 570,
		"mon_end": 900,
		"tues_start": 480,
		"tues_end": 990,
		"wed_start": 480,
		"wed_end": 990,
		"thurs_start": 0,
		"thurs_end": 0,
		"fri_start": 0,
		"fri_end": 0,
		"sat_start": 0,
		"sat_end": 0,
		"sun_start": 0,
		"sun_end": 0,
		"tags": [
			"paintball",
			"misc"
		],
		"price": -10
	},
	{
		"venue_id": "yelpeGj_eFdqqG8as7eZnovbAA",
		"event_name": "Fox Paintball",
		"event_id": "yelpeGj_eFdqqG8as7eZnovbAA",
		"mon_start": 0,
		"mon_end": 0,
		"tues_start": 0,
		"tues_end": 0,
		"wed_start": 0,
		"wed_end": 0,
		"thurs_start": 0,
		"thurs_end": 0,
		"fri_start": 0,
		"fri_end": 0,
		"sat_start": 0,
		"sat_end": 0,
		"sun_start": 0,
		"sun_end": 0,
		"tags": [
			"sportgoods",
			"misc",
			"eventplanning",
			"misc",
			"paintball",
			"misc"
		],
		"price": -2
	},
	{
		"venue_id": "yelpnkQ6lKjpokQvFVTKH2i-7g",
		"event_name": "Power Paintball",
		"event_id": "yelpnkQ6lKjpokQvFVTKH2i-7g",
		"mon_start": 900,
		"mon_end": 1260,
		"tues_start": 900,
		"tues_end": 1320,
		"wed_start": 600,
		"wed_end": 1320,
		"thurs_start": 660,
		"thurs_end": 1200,
		"fri_start": 0,
		"fri_end": 0,
		"sat_start": 0,
		"sat_end": 0,
		"sun_start": 0,
		"sun_end": 0,
		"tags": [
			"airsoft",
			"misc",
			"paintball",
			"misc"
		],
		"price": -10
	},
	{
		"venue_id": "yelpAiPFySR0XXIbyrDZ_2bEvg",
		"event_name": "Odyssey Fun World",
		"event_id": "yelpAiPFySR0XXIbyrDZ_2bEvg",
		"mon_start": 720,
		"mon_end": 1200,
		"tues_start": 720,
		"tues_end": 1260,
		"wed_start": 600,
		"wed_end": 1320,
		"thurs_start": 720,
		"thurs_end": 1200,
		"fri_start": 0,
		"fri_end": 0,
		"sat_start": 0,
		"sat_end": 0,
		"sun_start": 0,
		"sun_end": 0,
		"tags": [
			"paintball",
			"misc",
			"lasertag",
			"misc",
			"arcades",
			"misc"
		],
		"price": -10
	},
	{
		"venue_id": "yelpdzLOX_ZzrlHmVDaps2VUjg",
		"event_name": "Blast Camp",
		"event_id": "yelpdzLOX_ZzrlHmVDaps2VUjg",
		"mon_start": 600,
		"mon_end": 1020,
		"tues_start": 600,
		"tues_end": 1020,
		"wed_start": 600,
		"wed_end": 1020,
		"thurs_start": 600,
		"thurs_end": 1020,
		"fri_start": 600,
		"fri_end": 1020,
		"sat_start": 540,
		"sat_end": 960,
		"sun_start": 540,
		"sun_end": 960,
		"tags": [
			"paintball",
			"misc"
		],
		"price": -10
	},
	{
		"venue_id": "yelpD1tiY2ymPzVA2NLOAojxxQ",
		"event_name": "Legacy Adventure Park",
		"event_id": "yelpD1tiY2ymPzVA2NLOAojxxQ",
		"mon_start": 540,
		"mon_end": 1080,
		"tues_start": 540,
		"tues_end": 1080,
		"wed_start": 540,
		"wed_end": 1080,
		"thurs_start": 0,
		"thurs_end": 0,
		"fri_start": 0,
		"fri_end": 0,
		"sat_start": 0,
		"sat_end": 0,
		"sun_start": 0,
		"sun_end": 0,
		"tags": [
			"paintball",
			"misc",
			"airsoft",
			"misc",
			"lasertag",
			"misc"
		],
		"price": -10
	},
	{
		"venue_id": "yelpDGXoj3jR2D04tlltimUAnA",
		"event_name": "Undead Acres",
		"event_id": "yelpDGXoj3jR2D04tlltimUAnA",
		"mon_start": 1140,
		"mon_end": 1380,
		"tues_start": 1140,
		"tues_end": 1380,
		"wed_start": 1140,
		"wed_end": 1320,
		"thurs_start": 0,
		"thurs_end": 0,
		"fri_start": 0,
		"fri_end": 0,
		"sat_start": 0,
		"sat_end": 0,
		"sun_start": 0,
		"sun_end": 0,
		"tags": [
			"hauntedhouses",
			"misc",
			"paintball",
			"misc"
		],
		"price": -10
	},
	{
		"venue_id": "yelpYkb1qW9QPwICH4XiBXRvIw",
		"event_name": "Richmond Hunting Club",
		"event_id": "yelpYkb1qW9QPwICH4XiBXRvIw",
		"mon_start": 0,
		"mon_end": 0,
		"tues_start": 0,
		"tues_end": 0,
		"wed_start": 0,
		"wed_end": 0,
		"thurs_start": 0,
		"thurs_end": 0,
		"fri_start": 0,
		"fri_end": 0,
		"sat_start": 0,
		"sat_end": 0,
		"sun_start": 0,
		"sun_end": 0,
		"tags": [
			"paintball",
			"misc",
			"gun_ranges",
			"misc",
			"fishing",
			"misc"
		],
		"price": -10
	},
	{
		"venue_id": "yelpBDqjDPDiCWDbycsDAE9OHg",
		"event_name": "Mir Tactical",
		"event_id": "yelpBDqjDPDiCWDbycsDAE9OHg",
		"mon_start": 720,
		"mon_end": 1200,
		"tues_start": 720,
		"tues_end": 1200,
		"wed_start": 720,
		"wed_end": 1200,
		"thurs_start": 720,
		"thurs_end": 1200,
		"fri_start": 720,
		"fri_end": 1200,
		"sat_start": 600,
		"sat_end": 1080,
		"sun_start": 0,
		"sun_end": 0,
		"tags": [
			"paintball",
			"misc",
			"outdoorgear",
			"misc",
			"airsoft",
			"misc"
		],
		"price": -2
	},
	{
		"venue_id": "yelpaXvnafg2oG1I3F2Y3Vgp_Q",
		"event_name": "Warped Sportz",
		"event_id": "yelpaXvnafg2oG1I3F2Y3Vgp_Q",
		"mon_start": 840,
		"mon_end": 1140,
		"tues_start": 840,
		"tues_end": 1140,
		"wed_start": 660,
		"wed_end": 1140,
		"thurs_start": 660,
		"thurs_end": 1140,
		"fri_start": 660,
		"fri_end": 1140,
		"sat_start": 660,
		"sat_end": 1140,
		"sun_start": 660,
		"sun_end": 1080,
		"tags": [
			"paintball",
			"misc",
			"shoes",
			"misc",
			"skateshops",
			"misc"
		],
		"price": -10
	},
	{
		"venue_id": "yelppFwsS16keJP51dfm45h99Q",
		"event_name": "Rhc Paintball Fields",
		"event_id": "yelppFwsS16keJP51dfm45h99Q",
		"mon_start": 600,
		"mon_end": 1020,
		"tues_start": 540,
		"tues_end": 1020,
		"wed_start": 540,
		"wed_end": 1020,
		"thurs_start": 0,
		"thurs_end": 0,
		"fri_start": 0,
		"fri_end": 0,
		"sat_start": 0,
		"sat_end": 0,
		"sun_start": 0,
		"sun_end": 0,
		"tags": [
			"paintball",
			"misc"
		],
		"price": -10
	},
	{
		"venue_id": "yelpxlxftqc-Lmb7m0C7yLF9xw",
		"event_name": "Aggressive Paintball",
		"event_id": "yelpxlxftqc-Lmb7m0C7yLF9xw",
		"mon_start": 660,
		"mon_end": 1140,
		"tues_start": 660,
		"tues_end": 1140,
		"wed_start": 660,
		"wed_end": 1140,
		"thurs_start": 660,
		"thurs_end": 1140,
		"fri_start": 660,
		"fri_end": 1200,
		"sat_start": 660,
		"sat_end": 1140,
		"sun_start": 660,
		"sun_end": 960,
		"tags": [
			"sportgoods",
			"misc",
			"paintball",
			"misc"
		],
		"price": -2
	},
	{
		"venue_id": "yelpXzZHXVuWheRbRqP06uvMfA",
		"event_name": "Bad Boyz Toyz",
		"event_id": "yelpXzZHXVuWheRbRqP06uvMfA",
		"mon_start": 540,
		"mon_end": 1020,
		"tues_start": 480,
		"tues_end": 990,
		"wed_start": 480,
		"wed_end": 990,
		"thurs_start": 0,
		"thurs_end": 0,
		"fri_start": 0,
		"fri_end": 0,
		"sat_start": 0,
		"sat_end": 0,
		"sun_start": 0,
		"sun_end": 0,
		"tags": [
			"sportgoods",
			"misc",
			"paintball",
			"misc"
		],
		"price": -2
	},
	{
		"venue_id": "yelpztDQX0K9RGybar0Ihec74w",
		"event_name": "Paint Pursuit Games",
		"event_id": "yelpztDQX0K9RGybar0Ihec74w",
		"mon_start": 540,
		"mon_end": 840,
		"tues_start": 540,
		"tues_end": 840,
		"wed_start": 540,
		"wed_end": 840,
		"thurs_start": 540,
		"thurs_end": 840,
		"fri_start": 540,
		"fri_end": 840,
		"sat_start": 420,
		"sat_end": 1020,
		"sun_start": 420,
		"sun_end": 1020,
		"tags": [
			"paintball",
			"misc"
		],
		"price": -10
	},
	{
		"venue_id": "yelpAoxCefZF2NimlJRtjV18Gg",
		"event_name": "Chicago Paintball Field White Wolf",
		"event_id": "yelpAoxCefZF2NimlJRtjV18Gg",
		"mon_start": 0,
		"mon_end": 0,
		"tues_start": 0,
		"tues_end": 0,
		"wed_start": 0,
		"wed_end": 0,
		"thurs_start": 0,
		"thurs_end": 0,
		"fri_start": 0,
		"fri_end": 0,
		"sat_start": 0,
		"sat_end": 0,
		"sun_start": 0,
		"sun_end": 0,
		"tags": [
			"paintball",
			"misc"
		],
		"price": -10
	},
	{
		"venue_id": "yelpiA4p0TbR1Q1hjFLX3_epew",
		"event_name": "Promised Land Paint-Ball",
		"event_id": "yelpiA4p0TbR1Q1hjFLX3_epew",
		"mon_start": 0,
		"mon_end": 0,
		"tues_start": 0,
		"tues_end": 0,
		"wed_start": 0,
		"wed_end": 0,
		"thurs_start": 0,
		"thurs_end": 0,
		"fri_start": 0,
		"fri_end": 0,
		"sat_start": 0,
		"sat_end": 0,
		"sun_start": 0,
		"sun_end": 0,
		"tags": [
			"paintball",
			"misc"
		],
		"price": -10
	},
	{
		"venue_id": "yelpiJxeXgfDdTD5GT7SEf-U3w",
		"event_name": "Guts and Glory Paintball",
		"event_id": "yelpiJxeXgfDdTD5GT7SEf-U3w",
		"mon_start": 720,
		"mon_end": 1140,
		"tues_start": 720,
		"tues_end": 1140,
		"wed_start": 720,
		"wed_end": 1140,
		"thurs_start": 720,
		"thurs_end": 1140,
		"fri_start": 600,
		"fri_end": 1020,
		"sat_start": 0,
		"sat_end": 0,
		"sun_start": 0,
		"sun_end": 0,
		"tags": [
			"paintball",
			"misc"
		],
		"price": -10
	}
]